ssh_publish/__init__.py
ssh_publish/__main__.py
ssh_publish/py.typed
ssh_publish-1.0.0.dist-info/LICENSE
ssh_publish-1.0.0.dist-info/METADATA
ssh_publish-1.0.0.dist-info/WHEEL
ssh_publish-1.0.0.dist-info/entry_points.txt
ssh_publish-1.0.0.dist-info/top_level.txt
ssh_publish-1.0.0.dist-info/RECORD
