Metadata-Version: 2.2
Name: ssh-publish
Version: 1.0.0
Summary: Publish python packages to VPS via SSH
Author-email: Pradish Bijukchhe <pradish@sandbox.com.np>
License: Copyright (c) 2025 Pradish Bijukchhe
Project-URL: Homepage, https://github.com/sandbox-pokhara/ssh-publish
Project-URL: Issues, https://github.com/sandbox-pokhara/ssh-publish/issues
Classifier: Programming Language :: Python :: 3
Requires-Python: >=3
License-File: LICENSE
Requires-Dist: paramiko
